condor_log_utils/JobLog.py
condor_log_utils/__init__.py
condor_log_utils/_version.py
condor_log_utils/scaling_log_analyzer.py
ja_htcondor_log_utilities-0.0.4.dist-info/licenses/LICENSE
ja_htcondor_log_utilities-0.0.4.dist-info/METADATA
ja_htcondor_log_utilities-0.0.4.dist-info/WHEEL
ja_htcondor_log_utilities-0.0.4.dist-info/entry_points.txt
ja_htcondor_log_utilities-0.0.4.dist-info/top_level.txt
ja_htcondor_log_utilities-0.0.4.dist-info/RECORD
